legalysis/__init__.py
legalysis/main.py
legalysis/prompts.py
legalysis-2025.12.21190910.dist-info/METADATA
legalysis-2025.12.21190910.dist-info/WHEEL
legalysis-2025.12.21190910.dist-info/top_level.txt
legalysis-2025.12.21190910.dist-info/RECORD
