Metadata-Version: 2.4
Name: legalysis
Version: 2025.12.21190910
Summary: legalysis extracts parties, issues, outcomes, and lessons from case texts into a consistent, structured format for quick legal insight.
Author-email: legalysis <hi@eugene.plus>
License: MIT
Project-URL: Homepage, https://github.com/chigwell/legalysis
Requires-Python: >=3.9
Requires-Dist: langchain-llm7>=0.0.0
Requires-Dist: llmatch-messages>=0.0.0
Requires-Dist: langchain-core>=0.3.0
